tspwplib/__init__.py
tspwplib/complete.py
tspwplib/converter.py
tspwplib/exception.py
tspwplib/metric.py
tspwplib/problem.py
tspwplib/sparse.py
tspwplib/tsplib95.py
tspwplib/types.py
tspwplib/utils.py
tspwplib/walk.py
tspwplib-0.7.3.dist-info/LICENSE
tspwplib-0.7.3.dist-info/METADATA
tspwplib-0.7.3.dist-info/WHEEL
tspwplib-0.7.3.dist-info/top_level.txt
tspwplib-0.7.3.dist-info/RECORD
